{
  "generated_at": "2026-06-28T23:18:37Z",
  "checks": {
    "stripe": {"ok": false, "last_checked": "2026-06-28T23:18:37Z"},
    "worker": {"ok": false, "code": 200, "last_checked": "2026-06-28T23:18:37Z"},
    "runner": {"ok": false, "last_checked": "2026-06-28T23:18:37Z"},
    "email": {"ok": false, "last_checked": "2026-06-28T23:18:37Z"},
    "github": {"ok": false, "last_checked": "2026-06-28T23:18:37Z"},
    "pages": {"ok": true, "code": 200, "last_checked": "2026-06-28T23:18:37Z"},
    "audit_page": {"ok": true, "code": 200, "last_checked": "2026-06-28T23:18:37Z"},
    "pack_page": {"ok": true, "code": 200, "last_checked": "2026-06-28T23:18:37Z"},
    "ics_feed": {"ok": true, "code": 200, "last_checked": "2026-06-28T23:18:37Z"}
  },
  "metrics": {
    "audits_delivered_7d": 0,
    "prs_opened_7d": 0,
    "drift_watch_subscribers": 0
  }
}
